epicboxie/__init__.py
epicboxie/config.py
epicboxie/exceptions.py
epicboxie/sandboxes.py
epicboxie/utils.py
tests/__init__.py
tests/conftest.py
tests/test_sandboxes.py
tests/test_utils.py
tests/utils.py
epicboxie-1.1.1.dev4.dist-info/AUTHORS
epicboxie-1.1.1.dev4.dist-info/LICENSE
epicboxie-1.1.1.dev4.dist-info/METADATA
epicboxie-1.1.1.dev4.dist-info/WHEEL
epicboxie-1.1.1.dev4.dist-info/pbr.json
epicboxie-1.1.1.dev4.dist-info/top_level.txt
epicboxie-1.1.1.dev4.dist-info/RECORD
