Metadata-Version: 2.1
Name: epicboxie
Version: 1.1.1.dev4
Summary: EpicBox fork. Original package developers is StepicOrg.
Home-page: https://github.com/pashawnn/epicbox
Author: Pavel Shishmarev
Author-email: pashawnn@gmail.com
License: UNKNOWN
Platform: UNKNOWN
Classifier: Programming Language :: Python :: 3
Classifier: License :: OSI Approved :: MIT License
Classifier: Operating System :: POSIX :: Linux
Requires-Dist: docker (>=2)
Requires-Dist: python-dateutil (~=2.4)
Requires-Dist: requests (~=2.14)
Requires-Dist: structlog (>=15.3)
